opt_solver-0.1.2.dist-info/METADATA
opt_solver-0.1.2.dist-info/WHEEL
opt_solver/__init__.py
opt_solver/opt_solver.cp310-win_amd64.pyd
opt_solver-0.1.2.dist-info/RECORD
