Metadata-Version: 2.1
Name: opt_solver
Version: 0.1.2
Classifier: Programming Language :: Rust
Classifier: Programming Language :: Python :: Implementation :: CPython
Classifier: Programming Language :: Python :: Implementation :: PyPy
Summary: Common optimization algorithms
Keywords: opt,optimize,PSO
Author: HunLuanZhiZhu <zhuyihe@petalmail.com>
Author-email: HunLuanZhiZhu <zhuyihe@petalmail.com>
License: MIT OR Apache-2.0
Requires-Python: >=3.7
